no_config/__init__.py
no_config/config.py
no_config/inject.py
no_config-0.1.5.dist-info/METADATA
no_config-0.1.5.dist-info/WHEEL
no_config-0.1.5.dist-info/top_level.txt
no_config-0.1.5.dist-info/RECORD
