Metadata-Version: 2.1
Name: no-config
Version: 0.1.5
Summary: Simple configuration handling in Python.
Home-page: https://github.com/ncdhz/no_config
Author: ncdhz
Author-email: ncdhz@qq.com
Requires-Python: >=3.7
Requires-Dist: PyYAML
Requires-Dist: toml
